bcd_to_7seg.v
module bcd_to_7seg (
    input  wire [3:0] bcd,       // 4位 BCD 码输入
    output reg  [6:0] seg        // 7位段码输出 (a-g, 高电平点亮)
);

    always @(*) begin
        case (bcd)
            4'h0: seg = 7'b011_1111; // 0
            4'h1: seg = 7'b000_0110; // 1
            4'h2: seg = 7'b101_1011; // 2
            4'h3: seg = 7'b100_1111; // 3
            4'h4: seg = 7'b110_0110; // 4
            4'h5: seg = 7'b110_1101; // 5
            4'h6: seg = 7'b110_1111; // 6
            4'h7: seg = 7'b000_0111; // 7
            4'h8: seg = 7'b111_1111; // 8
            4'h9: seg = 7'b110_1111; // 9
            default: seg = 7'b000_0000;
        endcase
    end

endmodule

time_compare_enlight.v
module time_compare_enlight (
    input  wire       CLK_1kHz,      // 1kHz 时钟信号
    input  wire [3:0] start_h,       // 起始时间十位
    input  wire [3:0] start_l,       // 起始时间个位
    input  wire [3:0] end_h,         // 截止时间十位
    input  wire [3:0] end_l,         // 截止时间个位
    input  wire [3:0] timer_h_in,    // 当前倒计时十位
    input  wire [3:0] timer_l_in,    // 当前倒计时个位

    output reg  [7:0] led_sig        // 8路流水灯输出信号（低电平点亮）
);

    // ============================================================
    // 1. 分频逻辑：1kHz -> 10Hz
    // ============================================================
    reg [5:0] clk_cnt = 6'd0;
    reg       clk_10hz = 1'b0;

    always @(posedge CLK_1kHz) begin
        if (clk_cnt >= 6'd49) begin
            clk_cnt  <= 6'd0;
            clk_10hz <= ~clk_10hz;
        end else begin
            clk_cnt <= clk_cnt + 1'b1;
        end
    end

    // ============================================================
    // 2. 提取 10Hz 上升沿脉冲
    // ============================================================
    reg clk_10hz_d1 = 1'b0;
    reg clk_10hz_d2 = 1'b0;
    wire pulse_10hz;

    always @(posedge CLK_1kHz) begin
        clk_10hz_d1 <= clk_10hz;
        clk_10hz_d2 <= clk_10hz_d1;
    end

    assign pulse_10hz = clk_10hz_d1 && (~clk_10hz_d2);

    // ============================================================
    // 3. 时间比较
    //
    // 倒计时是从 Start 向 End 递减：
    //
    //     Start >= Current >= End
    //
    // 例如：
    //     Start = 50
    //     End   = 10
    //
    //     50, 49, 48, ... 11, 10
    //     都属于有效区间
    // ============================================================
    wire [7:0] current_time;
    wire [7:0] start_time;
    wire [7:0] end_time;

    assign current_time = {timer_h_in, timer_l_in};
    assign start_time   = {start_h, start_l};
    assign end_time     = {end_h, end_l};

    wire in_range;

    assign in_range =
        (start_time >= end_time) &&
        (current_time <= start_time) &&
        (current_time >= end_time);

    // ============================================================
    // 4. 8路流水灯计数器
    // ============================================================
    reg [2:0] led_cnt = 3'd0;

    always @(posedge CLK_1kHz) begin
        if (!in_range) begin
            led_cnt <= 3'd0;
        end else if (pulse_10hz) begin
            led_cnt <= led_cnt + 1'b1;
        end
    end

    // ============================================================
    // 5. 74138 译码逻辑
    //
    // 低电平点亮，因此任意时刻只有一路为 0。
    // ============================================================
    always @(*) begin
        if (in_range) begin
            case (led_cnt)
                3'b000: led_sig = 8'b1111_1110;
                3'b001: led_sig = 8'b1111_1101;
                3'b010: led_sig = 8'b1111_1011;
                3'b011: led_sig = 8'b1111_0111;
                3'b100: led_sig = 8'b1110_1111;
                3'b101: led_sig = 8'b1101_1111;
                3'b110: led_sig = 8'b1011_1111;
                3'b111: led_sig = 8'b0111_1111;
                default: led_sig = 8'b1111_1111;
            endcase
        end else begin
            led_sig = 8'b1111_1111;
        end
    end

endmodule

err_select_display.v
module err_select_display (
    input  wire [3:0] start_h,      // 起始时间十位 (BCD)
    input  wire [3:0] start_l,      // 起始时间个位 (BCD)
    input  wire [3:0] end_h,        // 截止时间十位 (BCD)
    input  wire [3:0] end_l,        // 截止时间个位 (BCD)
    input  wire [3:0] timer_h_in,   // 当前倒计时十位 (BCD)
    input  wire [3:0] timer_l_in,   // 当前倒计时个位 (BCD)
    
    output wire       auto_load,    // 错误自动重载信号 (高电平表示 Start < End)
    output wire [6:0] timer_h_out,  // 十位数码管最终段码输出
    output wire [6:0] timer_l_out   // 个位数码管最终段码输出
);

    // 1. err_compare 逻辑：比较 Start 与 End 的大小 (两片 7485 级联)
    // 当 Start > End 时，is_error 触发拉高
    wire is_error;
	assign is_error = ({start_h, start_l} < {end_h, end_l});
    assign auto_load = is_error;

    // 2. err_bcd_7seg 逻辑：将当前倒计时 BCD 转为 7 段数码管段码 (7448 逻辑，高电平点亮)
    reg [6:0] normal_h_seg;
    reg [6:0] normal_l_seg;

    function [6:0] bcd2seg(input [3:0] bcd);
        case (bcd)
            4'h0: bcd2seg = 7'b011_1111; // 0
            4'h1: bcd2seg = 7'b000_0110; // 1
            4'h2: bcd2seg = 7'b101_1011; // 2
            4'h3: bcd2seg = 7'b100_1111; // 3
            4'h4: bcd2seg = 7'b110_0110; // 4
            4'h5: bcd2seg = 7'b110_1101; // 5
            4'h6: bcd2seg = 7'b110_1111; // 6
            4'h7: bcd2seg = 7'b000_0111; // 7
            4'h8: bcd2seg = 7'b111_1111; // 8
            4'h9: bcd2seg = 7'b110_1111; // 9
            default: bcd2seg = 7'b000_0000;
        endcase
    endfunction

    always @(*) begin
        normal_h_seg = bcd2seg(timer_h_in);
        normal_l_seg = bcd2seg(timer_l_in);
    end

    // 3. 错误状态硬编码段码 (根据原理图中 74157 接 VCC/GND 的高低电平值设定)
    // 对应显示 "E" (十位) 和 "r" (个位) 的 7 段图形
    localparam [6:0] SEG_ERR_H = 7'b111_1001; // 十位显示 'E'
    localparam [6:0] SEG_ERR_L = 7'b101_0000; // 个位显示 'r'

    // 4. err_mux_h 和 err_mux_l 逻辑：74157 数据二选一选择器
    // is_error 为 1 时输出错误段码；为 0 时输出正常倒计时段码
    assign timer_h_out = is_error ? SEG_ERR_H : normal_h_seg;
    assign timer_l_out = is_error ? SEG_ERR_L : normal_l_seg;

endmodule

timer_main.v
module timer_main (
    input  wire       CLK_1kHz,       // 1kHz 输入时钟
    input  wire       reset_total,    // 低电平有效的全局同步预置/复位信号
    output reg  [3:0] timer_h_in,     // 倒计时十位 BCD 码
    output reg  [3:0] timer_l_in,     // 倒计时个位 BCD 码
    output wire       timer_reset     // 归零/重置脉冲信号
);

    // 1. 内部分频计数器：1kHz -> 1Hz (1000个周期产生一个1Hz脉冲)
    reg [9:0] clk_cnt = 10'd0;
    reg       clk_1hz = 1'b0;

    always @(posedge CLK_1kHz) begin
        if (clk_cnt >= 10'd499) begin
            clk_cnt <= 10'd0;
            clk_1hz <= ~clk_1hz;      // 翻转产生 1Hz 方波
        end else begin
            clk_cnt <= clk_cnt + 1'b1;
        end
    end

    // 提取 1Hz 信号的上升沿脉冲，避免时钟域同步问题
    reg clk_1hz_d1, clk_1hz_d2;
    wire pulse_1hz;

    always @(posedge CLK_1kHz) begin
        clk_1hz_d1 <= clk_1hz;
        clk_1hz_d2 <= clk_1hz_d1;
    end
    assign pulse_1hz = clk_1hz_d1 && (~clk_1hz_d2);

    // 2. 60秒 BCD 减法计数逻辑 (模拟两片 74192)
    always @(posedge CLK_1kHz) begin
        if (!reset_total) begin
            // 低电平预置/复位，初始重置为 60 秒
            timer_h_in <= 4'd6;
            timer_l_in <= 4'd0;
        end else if (pulse_1hz) begin
            if (timer_l_in == 4'd0) begin
                if (timer_h_in == 4'd0) begin
                    // 计数到 00 秒时自动回到 60 秒
                    timer_h_in <= 4'd6;
                    timer_l_in <= 4'd0;
                end else begin
                    // 个位借位：个位变为 9，十位减 1
                    timer_l_in <= 4'd9;
                    timer_h_in <= timer_h_in - 1'b1;
                end
            end else begin
                // 个位正常递减
                timer_l_in <= timer_l_in - 1'b1;
            end
        end
    end

    // 3. 原理图中的 AND2 复位信号输出逻辑
    // 当倒计时减至 00 秒时输出高电平脉冲
    assign timer_reset = (timer_h_in == 4'd0) && (timer_l_in == 4'd0);

endmodule

key_set_timer.v
module key_set_timer (
    input  wire       CLK_1kHz,    // 1kHz 时钟信号
    input  wire [3:0] row,         // 键盘行输入信号

    output wire [3:0] col,         // 键盘列输出信号（第一列接 GND，其余拉高）
    output reg  [3:0] start_h = 4'd0,  // 起始十位，初值 0
    output reg  [3:0] start_l = 4'd0,  // 起始个位，初值 0
    output reg  [3:0] end_h   = 4'd0,  // 截止十位，初值 0
    output reg  [3:0] end_l   = 4'd0   // 截止个位，初值 0
);

    // 列线电平固定：col[0]=0, col[3..1]=1
    assign col = 4'b1110;

    // 1. key_debounce：两级触发器消抖同步
    reg [3:0] row_sync_0 = 4'b0000;
    reg [3:0] row_sync_1 = 4'b0000;

    always @(posedge CLK_1kHz) begin
        row_sync_0 <= row;
        row_sync_1 <= row_sync_0;
    end

    // 2. key_edge_detect：提取按键按下边沿脉冲
    reg [3:0] row_sync_2 = 4'b0000;

    always @(posedge CLK_1kHz) begin
        row_sync_2 <= row_sync_1;
    end

    // 按键按压触发脉冲（高电平有效）
    wire [3:0] key_pressed;
    assign key_pressed = row_sync_1 & (~row_sync_2);

    // 3. key_counters：4 位按键设定计数器
    // key_pressed[0] -> start_h (模 6: 0-5)
    // key_pressed[1] -> start_l (模 10: 0-9)
    // key_pressed[2] -> end_h   (模 6: 0-5)
    // key_pressed[3] -> end_l   (模 10: 0-9)

    // start_h 计数器 (0~5)
    always @(posedge CLK_1kHz) begin
        if (key_pressed[0]) begin
            if (start_h >= 4'd5)
                start_h <= 4'd0;
            else
                start_h <= start_h + 1'b1;
        end
    end

    // start_l 计数器 (0~9)
    always @(posedge CLK_1kHz) begin
        if (key_pressed[1]) begin
            if (start_l >= 4'd9)
                start_l <= 4'd0;
            else
                start_l <= start_l + 1'b1;
        end
    end

    // end_h 计数器 (0~5)
    always @(posedge CLK_1kHz) begin
        if (key_pressed[2]) begin
            if (end_h >= 4'd5)
                end_h <= 4'd0;
            else
                end_h <= end_h + 1'b1;
        end
    end

    // end_l 计数器 (0~9)
    always @(posedge CLK_1kHz) begin
        if (key_pressed[3]) begin
            if (end_l >= 4'd9)
                end_l <= 4'd0;
            else
                end_l <= end_l + 1'b1;
        end
    end

endmodule

timer_top.v
// 顶层模块：打通原理图中的各子模块与逻辑门电路
module timer_top (
    input  wire       clk_1khz,       // 1kHz 时钟信号 (PIN_18)
    input  wire       reset,          // 外部复位按键 (PIN_20)
    input  wire [3:0] row,            // 矩阵键盘行输入 (PIN_23, 24, 27, 28)
    
    output wire [3:0] col,            // 矩阵键盘列扫描输出 (PIN_29, 30, 31, 32)
    output wire [6:0] timer_h_out,    // 主倒计时十位数码管段码 (PIN_102...104)
    output wire [6:0] timer_l_out,    // 主倒计时个位数码管段码 (PIN_88...94)
    output wire [7:0] led_out,        // 8路流水灯/状态指示灯 (PIN_1...8)
    
    // 设置参数显示数码管 (对应原图 4 片 7448 译码器输出)
    output wire [6:0] start_h_seg,    // 起始时间十位 (PIN_140...142)
    output wire [6:0] start_l_seg,    // 起始时间个位 (PIN_130...132)
    output wire [6:0] end_h_seg,      // 截止时间十位 (PIN_120...122)
    output wire [6:0] end_l_seg       // 截止时间个位 (PIN_110...112)
);

    // 内部连线信号声明
    wire [3:0] start_h, start_l;
    wire [3:0] end_h, end_l;
    wire [3:0] timer_h_in, timer_l_in;
    
    wire       auto_load;
    wire       timer_reset;
    wire       reset_total;
    wire [7:0] led_sig;

    // 1. 原理图中的 NOR3 门逻辑: reset_total = ~(auto_load | reset | timer_reset)
    assign reset_total = ~(auto_load | reset | timer_reset);

    // 2. 原理图中的 NOT 门逻辑: 取反驱动 LED (低电平点亮)
    assign led_out = ~led_sig;

    // 3. 矩阵键盘与时间设置模块
    key_set_timer u_key_set_timer (
        .CLK_1kHz (clk_1khz),
        .row      (row),
        .col      (col),
        .start_h  (start_h),
        .start_l  (start_l),
        .end_h    (end_h),
        .end_l    (end_l)
    );

    // 4. 倒计时主控模块
    timer_main u_timer_main (
        .CLK_1kHz    (clk_1khz),
        .reset_total (reset_total),
        .timer_h_in  (timer_h_in),
        .timer_l_in  (timer_l_in),
        .timer_reset (timer_reset)
    );

    // 5. 错误检测与倒计时显示控制模块
    err_select_display u_err_select_display (
        .start_h     (start_h),
        .start_l     (start_l),
        .end_h       (end_h),
        .end_l       (end_l),
        .timer_h_in  (timer_h_in),
        .timer_l_in  (timer_l_in),
        .auto_load   (auto_load),
        .timer_h_out (timer_h_out),
        .timer_l_out (timer_l_out)
    );

    // 6. 流水灯控制模块
    time_compare_enlight u_time_compare_enlight (
        .CLK_1kHz   (clk_1khz),
        .start_h    (start_h),
        .start_l    (start_l),
        .end_h      (end_h),
        .end_l      (end_l),
        .timer_h_in (timer_h_in),
        .timer_l_in (timer_l_in),
        .led_sig    (led_sig)
    );

    // 7. 4 片 7448 译码器替换 (用于 start/end 时间的静态译码显示)
    bcd_to_7seg u_dec_start_h (.bcd(start_h), .seg(start_h_seg));
    bcd_to_7seg u_dec_start_l (.bcd(start_l), .seg(start_l_seg));
    bcd_to_7seg u_dec_end_h   (.bcd(end_h),   .seg(end_h_seg));
    bcd_to_7seg u_dec_end_l   (.bcd(end_l),   .seg(end_l_seg));

endmodule

tb_timer_top_error.v
// ============================================================================
// 测试平台: tb_timer_top.v  (改版: 宽窗口 [45,55] + Er 错误场景)
// ============================================================================
`timescale 1ns/1ps

module tb_timer_top;

    parameter CLK_PERIOD = 10;   // 仿真时钟周期 10ns, 逻辑上等效 1kHz

    reg        clk_1khz;
    reg        reset;
    reg  [3:0] row;

    wire [3:0] col;
    wire [6:0] timer_h_out;
    wire [6:0] timer_l_out;
    wire [7:0] led_out;
    wire [6:0] start_h_seg;
    wire [6:0] start_l_seg;
    wire [6:0] end_h_seg;
    wire [6:0] end_l_seg;

    timer_top dut (
        .clk_1khz    (clk_1khz),
        .reset       (reset),
        .row         (row),
        .col         (col),
        .timer_h_out (timer_h_out),
        .timer_l_out (timer_l_out),
        .led_out     (led_out),
        .start_h_seg (start_h_seg),
        .start_l_seg (start_l_seg),
        .end_h_seg   (end_h_seg),
        .end_l_seg   (end_l_seg)
    );

    initial clk_1khz = 1'b0;
    always #(CLK_PERIOD/2) clk_1khz = ~clk_1khz;

    // 观测信号 (方便 VCD 抓取)
    wire [3:0] start_h       = dut.start_h;
    wire [3:0] start_l       = dut.start_l;
    wire [3:0] end_h         = dut.end_h;
    wire [3:0] end_l         = dut.end_l;
    wire [3:0] timer_h       = dut.timer_h_in;
    wire [3:0] timer_l       = dut.timer_l_in;
    wire       auto_load     = dut.auto_load;
    wire       timer_reset_s = dut.timer_reset;
    wire       reset_total   = dut.reset_total;
    wire [7:0] led_sig       = dut.led_sig;
    wire [2:0] led_cnt       = dut.u_time_compare_enlight.led_cnt;
    wire       in_range      = dut.u_time_compare_enlight.in_range;
    wire       is_error      = dut.u_err_select_display.is_error;

    initial begin
        $dumpfile("tb_timer_top.vcd");
        $dumpvars(0, tb_timer_top);
    end

    // 一次按键 = 一个上升沿脉冲
    task press_key(input integer idx);
        begin
            @(posedge clk_1khz);
            #(CLK_PERIOD/4);
            row[idx] = 1'b1;
            #(CLK_PERIOD * 4);
            row[idx] = 1'b0;
            #(CLK_PERIOD * 4);
        end
    endtask

    task show_state(input [8*40-1:0] tag);
        begin
            $display("[%0t] %s | start=%d%d end=%d%d timer=%d%d | err=%b range=%b led=%b",
                     $time, tag,
                     start_h, start_l, end_h, end_l,
                     timer_h, timer_l,
                     is_error, in_range, led_sig);
        end
    endtask

    initial begin
        clk_1khz = 1'b0;
        reset    = 1'b1;
        row      = 4'b0000;

        $display("==========================================================");
        $display("  timer_top TB  --  window=[45,55] + Er scenario");
        $display("==========================================================");

        // ------------------------------------------------------------------
        // Phase 1: 复位, 倒计时应为 60
        // ------------------------------------------------------------------
        $display("\n--- Phase 1: Assert reset ---");
        #(CLK_PERIOD * 50);
        show_state("reset asserted");

        // ------------------------------------------------------------------
        // Phase 2: 释放复位, 观察 60->59->58
        //   1 个倒计时秒 = 1000 个 clk (1000 * 10ns = 10us 仿真时间)
        // ------------------------------------------------------------------
        $display("\n--- Phase 2: Release reset, countdown 60->59->58 ---");
        reset = 1'b0;
        #(CLK_PERIOD * 100);
        show_state("t~0.1s");

        #(CLK_PERIOD * 1100);
        show_state("t~1.2s  (should show 59)");

        #(CLK_PERIOD * 1000);
        show_state("t~2.2s  (should show 58)");

        // ------------------------------------------------------------------
        // Phase 3: 设置合法宽窗口  start=55, end=45
        //   此刻四个键盘计数器初值均为 0, 直接 repeat 到目标值
        // ------------------------------------------------------------------
        $display("\n--- Phase 3: Configure start=55, end=45 (legal wide window) ---");
        repeat(5) press_key(0);   // start_h: 0 -> 5
        repeat(5) press_key(1);   // start_l: 0 -> 5
        repeat(4) press_key(2);   // end_h:   0 -> 4
        repeat(5) press_key(3);   // end_l:   0 -> 5
        #(CLK_PERIOD * 20);
        show_state("start=55 end=45 set");

        // ------------------------------------------------------------------
        // Phase 4: 观察倒计时穿窗
        //   从 60 减到 55 需要 5 秒 = 5000 clk
        //   55 到 45 是窗口内 = 10000 clk (流水灯会走 100 步)
        // ------------------------------------------------------------------
        $display("\n--- Phase 4: Watch countdown crossing window [55..45] ---");

        #(CLK_PERIOD * 5000);
        show_state("countdown ~55 (ENTER window, marquee ON)");

        #(CLK_PERIOD * 3000);
        show_state("countdown ~52 (inside window, marquee walking)");

        #(CLK_PERIOD * 3000);
        show_state("countdown ~49 (inside window, marquee walking)");

        #(CLK_PERIOD * 4000);
        show_state("countdown ~45 (EXIT window edge)");

        #(CLK_PERIOD * 2000);
        show_state("countdown ~43 (out of window, LEDs blank)");

        // ------------------------------------------------------------------
        // Phase 5: 一路减到 00, 观察 timer_reset 脉冲与自动回卷 60
        //   43 秒 = 43000 clk
        // ------------------------------------------------------------------
        $display("\n--- Phase 5: Countdown to 00 -> timer_reset -> reload 60 ---");
        #(CLK_PERIOD * 43000);
        show_state("countdown reached 00 (timer_reset pulses here)");

        #(CLK_PERIOD * 1000);
        show_state("auto-reloaded to 60");

        // ------------------------------------------------------------------
        // Phase 6: 非法场景  start=10, end=30  (start < end -> is_error=1)
        //   当前:  start_h=5, start_l=5, end_h=4, end_l=5
        //   目标:  start_h=1, start_l=0, end_h=3, end_l=0
        //   模 6 / 模 10 计数, 按差值求次数:
        //     start_h: 5 -> 0 -> 1        (2 次)
        //     start_l: 5 -> 6..9 -> 0     (5 次)
        //     end_h:   4 -> 5 -> 0..2 -> 3(5 次)
        //     end_l:   5 -> 6..9 -> 0     (5 次)
        // ------------------------------------------------------------------
        $display("\n--- Phase 6: Configure start=10, end=30 (illegal) ---");
        repeat(2) press_key(0);
        repeat(5) press_key(1);
        repeat(5) press_key(2);
        repeat(5) press_key(3);
        #(CLK_PERIOD * 20);
        show_state("start=10 end=30 set  => is_error should be 1");

        // ------------------------------------------------------------------
        // Phase 7: 观察 Er 显示稳定
        // ------------------------------------------------------------------
        $display("\n--- Phase 7: Observe Er display and blanked LEDs ---");
        #(CLK_PERIOD * 5000);
        show_state("Er state stable");

        $display("\n==========================================================");
        $display("  Simulation complete.");
        $display("  Open tb_timer_top.vcd in GTKWave.");
        $display("==========================================================");
        $finish;
    end

endmodule

tb_timer_top_error.vcd
$date
	Tue Sep 15 21:21:01 2026
$end
$version
	Icarus Verilog
$end
$timescale
	1ps
$end
$scope module tb_timer_top $end
$var wire 1 ! auto_load $end
$var wire 4 " col [3:0] $end
$var wire 4 # end_h [3:0] $end
$var wire 4 $ end_l [3:0] $end
$var wire 1 % in_range $end
$var wire 1 & is_error $end
$var wire 3 ' led_cnt [2:0] $end
$var wire 8 ( led_sig [7:0] $end
$var wire 1 ) reset_total $end
$var wire 4 * start_h [3:0] $end
$var wire 4 + start_l [3:0] $end
$var wire 4 , timer_h [3:0] $end
$var wire 4 - timer_l [3:0] $end
$var wire 1 . timer_reset_s $end
$var wire 7 / timer_l_out [6:0] $end
$var wire 7 0 timer_h_out [6:0] $end
$var wire 7 1 start_l_seg [6:0] $end
$var wire 7 2 start_h_seg [6:0] $end
$var wire 8 3 led_out [7:0] $end
$var wire 7 4 end_l_seg [6:0] $end
$var wire 7 5 end_h_seg [6:0] $end
$var parameter 32 6 CLK_PERIOD $end
$var reg 1 7 clk_1khz $end
$var reg 1 8 reset $end
$var reg 4 9 row [3:0] $end
$scope module dut $end
$var wire 1 7 clk_1khz $end
$var wire 4 : col [3:0] $end
$var wire 8 ; led_out [7:0] $end
$var wire 1 8 reset $end
$var wire 1 < reset_total $end
$var wire 4 = row [3:0] $end
$var wire 1 > timer_reset $end
$var wire 7 ? timer_l_out [6:0] $end
$var wire 4 @ timer_l_in [3:0] $end
$var wire 7 A timer_h_out [6:0] $end
$var wire 4 B timer_h_in [3:0] $end
$var wire 7 C start_l_seg [6:0] $end
$var wire 4 D start_l [3:0] $end
$var wire 7 E start_h_seg [6:0] $end
$var wire 4 F start_h [3:0] $end
$var wire 8 G led_sig [7:0] $end
$var wire 7 H end_l_seg [6:0] $end
$var wire 4 I end_l [3:0] $end
$var wire 7 J end_h_seg [6:0] $end
$var wire 4 K end_h [3:0] $end
$var wire 1 L auto_load $end
$scope module u_dec_end_h $end
$var wire 4 M bcd [3:0] $end
$var reg 7 N seg [6:0] $end
$upscope $end
$scope module u_dec_end_l $end
$var wire 4 O bcd [3:0] $end
$var reg 7 P seg [6:0] $end
$upscope $end
$scope module u_dec_start_h $end
$var wire 4 Q bcd [3:0] $end
$var reg 7 R seg [6:0] $end
$upscope $end
$scope module u_dec_start_l $end
$var wire 4 S bcd [3:0] $end
$var reg 7 T seg [6:0] $end
$upscope $end
$scope module u_err_select_display $end
$var wire 1 L auto_load $end
$var wire 7 U timer_l_out [6:0] $end
$var wire 4 V timer_l_in [3:0] $end
$var wire 7 W timer_h_out [6:0] $end
$var wire 4 X timer_h_in [3:0] $end
$var wire 4 Y start_l [3:0] $end
$var wire 4 Z start_h [3:0] $end
$var wire 1 [ is_error $end
$var wire 4 \ end_l [3:0] $end
$var wire 4 ] end_h [3:0] $end
$var parameter 7 ^ SEG_ERR_H $end
$var parameter 7 _ SEG_ERR_L $end
$var reg 7 ` normal_h_seg [6:0] $end
$var reg 7 a normal_l_seg [6:0] $end
$scope function bcd2seg $end
$var reg 4 b bcd [3:0] $end
$upscope $end
$upscope $end
$scope module u_key_set_timer $end
$var wire 1 7 CLK_1kHz $end
$var wire 4 c col [3:0] $end
$var wire 4 d key_pressed [3:0] $end
$var wire 4 e row [3:0] $end
$var reg 4 f end_h [3:0] $end
$var reg 4 g end_l [3:0] $end
$var reg 4 h row_sync_0 [3:0] $end
$var reg 4 i row_sync_1 [3:0] $end
$var reg 4 j row_sync_2 [3:0] $end
$var reg 4 k start_h [3:0] $end
$var reg 4 l start_l [3:0] $end
$upscope $end
$scope module u_time_compare_enlight $end
$var wire 1 7 CLK_1kHz $end
$var wire 4 m end_h [3:0] $end
$var wire 4 n end_l [3:0] $end
$var wire 1 o in_range $end
$var wire 1 p pulse_10hz $end
$var wire 4 q start_h [3:0] $end
$var wire 4 r start_l [3:0] $end
$var wire 4 s timer_l_in [3:0] $end
$var wire 4 t timer_h_in [3:0] $end
$var wire 8 u start_time [7:0] $end
$var wire 8 v end_time [7:0] $end
$var wire 8 w current_time [7:0] $end
$var reg 1 x clk_10hz $end
$var reg 1 y clk_10hz_d1 $end
$var reg 1 z clk_10hz_d2 $end
$var reg 6 { clk_cnt [5:0] $end
$var reg 3 | led_cnt [2:0] $end
$var reg 8 } led_sig [7:0] $end
$upscope $end
$scope module u_timer_main $end
$var wire 1 7 CLK_1kHz $end
$var wire 1 ~ pulse_1hz $end
$var wire 1 < reset_total $end
$var wire 1 > timer_reset $end
$var reg 1 !" clk_1hz $end
$var reg 1 "" clk_1hz_d1 $end
$var reg 1 #" clk_1hz_d2 $end
$var reg 10 $" clk_cnt [9:0] $end
$var reg 4 %" timer_h_in [3:0] $end
$var reg 4 &" timer_l_in [3:0] $end
$upscope $end
$upscope $end
$scope task press_key $end
$var integer 32 '" idx [31:0] $end
$upscope $end
$scope task show_state $end
$var reg 320 (" tag [319:0] $end
$upscope $end
$upscope $end
$enddefinitions $end
$comment Show the parameter values. $end
$dumpall
b1010000 _
b1111001 ^
b1010 6
$end
#0
$dumpvars
bx ("
bx '"
bx &"
bx %"
b0 $"
x#"
x""
0!"
x~
b11111111 }
b0 |
b0 {
0z
0y
0x
bx w
b0 v
b0 u
bx t
bx s
b0 r
b0 q
0p
xo
b0 n
b0 m
b0 l
b0 k
b0 j
b0 i
b0 h
b0 g
b0 f
b0 e
b0 d
b1110 c
bx b
bx a
bx `
b0 ]
b0 \
0[
b0 Z
b0 Y
bx X
bx W
bx V
bx U
b111111 T
b0 S
b111111 R
b0 Q
b111111 P
b0 O
b111111 N
b0 M
0L
b0 K
b111111 J
b0 I
b111111 H
b11111111 G
b0 F
b111111 E
b0 D
b111111 C
bx B
bx A
bx @
bx ?
x>
b0 =
0<
b0 ;
b1110 :
b0 9
18
07
b111111 5
b111111 4
b0 3
b111111 2
b111111 1
bx 0
bx /
x.
bx -
bx ,
b0 +
b0 *
0)
b11111111 (
b0 '
0&
x%
b0 $
b0 #
b1110 "
0!
$end
#5000
0%
0o
b111111 /
b111111 ?
b111111 U
b1101111 0
b1101111 A
b1101111 W
0~
0.
0>
b111111 a
b1101111 `
b0 b
b1 $"
0""
b0 -
b0 @
b0 V
b0 s
b0 &"
b1100000 w
b110 ,
b110 B
b110 X
b110 t
b110 %"
b1 {
17
#10000
07
#15000
b10 {
0#"
b10 $"
17
#20000
07
#25000
b11 $"
b11 {
17
#30000
07
#35000
b100 {
b100 $"
17
#40000
07
#45000
b101 $"
b101 {
17
#50000
07
#55000
b110 {
b110 $"
17
#60000
07
#65000
b111 $"
b111 {
17
#70000
07
#75000
b1000 {
b1000 $"
17
#80000
07
#85000
b1001 $"
b1001 {
17
#90000
07
#95000
b1010 {
b1010 $"
17
#100000
07
#105000
b1011 $"
b1011 {
17
#110000
07
#115000
b1100 {
b1100 $"
17
#120000
07
#125000
b1101 $"
b1101 {
17
#130000
07
#135000
b1110 {
b1110 $"
17
#140000
07
#145000
b1111 $"
b1111 {
17
#150000
07
#155000
b10000 {
b10000 $"
17
#160000
07
#165000
b10001 $"
b10001 {
17
#170000
07
#175000
b10010 {
b10010 $"
17
#180000
07
#185000
b10011 $"
b10011 {
17
#190000
07
#195000
b10100 {
b10100 $"
17
#200000
07
#205000
b10101 $"
b10101 {
17
#210000
07
#215000
b10110 {
b10110 $"
17
#220000
07
#225000
b10111 $"
b10111 {
17
#230000
07
#235000
b11000 {
b11000 $"
17
#240000
07
#245000
b11001 $"
b11001 {
17
#250000
07
#255000
b11010 {
b11010 $"
17
#260000
07
#265000
b11011 $"
b11011 {
17
#270000
07
#275000
b11100 {
b11100 $"
17
#280000
07
#285000
b11101 $"
b11101 {
17
#290000
07
#295000
b11110 {
b11110 $"
17
#300000
07
#305000
b11111 $"
b11111 {
17
#310000
07
#315000
b100000 {
b100000 $"
17
#320000
07
#325000
b100001 $"
b100001 {
17
#330000
07
#335000
b100010 {
b100010 $"
17
#340000
07
#345000
b100011 $"
b100011 {
17
#350000
07
#355000
b100100 {
b100100 $"
17
#360000
07
#365000
b100101 $"
b100101 {
17
#370000
07
#375000
b100110 {
b100110 $"
17
#380000
07
#385000
b100111 $"
b100111 {
17
#390000
07
#395000
b101000 {
b101000 $"
17
#400000
07
#405000
b101001 $"
b101001 {
17
#410000
07
#415000
b101010 {
b101010 $"
17
#420000
07
#425000
b101011 $"
b101011 {
17
#430000
07
#435000
b101100 {
b101100 $"
17
#440000
07
#445000
b101101 $"
b101101 {
17
#450000
07
#455000
b101110 {
b101110 $"
17
#460000
07
#465000
b101111 $"
b101111 {
17
#470000
07
#475000
b110000 {
b110000 $"
17
#480000
07
#485000
b110001 $"
b110001 {
17
#490000
07
#495000
1x
b0 {
b110010 $"
17
#500000
1)
1<
07
08
b111001001100101011100110110010101110100001000000110000101110011011100110110010101110010011101000110010101100100 ("
#505000
1p
b110011 $"
b1 {
1y
17
#510000
07
#515000
0p
1z
b10 {
b110100 $"
17
#520000
07
#525000
b110101 $"
b11 {
17
#530000
07
#535000
b100 {
b110110 $"
17
#540000
07
#545000
b110111 $"
b101 {
17
#550000
07
#555000
b110 {
b111000 $"
17
#560000
07
#565000
b111001 $"
b111 {
17
#570000
07
#575000
b1000 {
b111010 $"
17
#580000
07
#585000
b111011 $"
b1001 {
17
#590000
07
#595000
b1010 {
b111100 $"
17
#600000
07
#605000
b111101 $"
b1011 {
17
#610000
07
#615000
b1100 {
b111110 $"
17
#620000
07
#625000
b111111 $"
b1101 {
17
#630000
07
#635000
b1110 {
b1000000 $"
17
#640000
07
#645000
b1000001 $"
b1111 {
17
#650000
07
#655000
b10000 {
b1000010 $"
17
#660000
07
#665000
b1000011 $"
b10001 {
17
#670000
07
#675000
b10010 {
b1000100 $"
17
#680000
07
#685000
b1000101 $"
b10011 {
17
#690000
07
#695000
b10100 {
b1000110 $"
17
#700000
07
#705000
b1000111 $"
b10101 {
17
#710000
07
#715000
b10110 {
b1001000 $"
17
#720000
07
#725000
b1001001 $"
b10111 {
17
#730000
07
#735000
b11000 {
b1001010 $"
17
#740000
07
#745000
b1001011 $"
b11001 {
17
#750000
07
#755000
b11010 {
b1001100 $"
17
#760000
07
#765000
b1001101 $"
b11011 {
17
#770000
07
#775000
b11100 {
b1001110 $"
17
#780000
07
#785000
b1001111 $"
b11101 {
17
#790000
07
#795000
b11110 {
b1010000 $"
17
#800000
07
#805000
b1010001 $"
b11111 {
17
#810000
07
#815000
b100000 {
b1010010 $"
17
#820000
07
#825000
b1010011 $"
b100001 {
17
#830000
07
#835000
b100010 {
b1010100 $"
17
#840000
07
#845000
b1010101 $"
b100011 {
17
#850000
07
#855000
b100100 {
b1010110 $"
17
#860000
07
#865000
b1010111 $"
b100101 {
17
#870000
07
